tidychef/__init__.py
tidychef/acquire/__init__.py
tidychef/acquire/base.py
tidychef/acquire/csv/__init__.py
tidychef/acquire/csv/http_implemented.py
tidychef/acquire/csv/local_implemented.py
tidychef/acquire/excel_time.py
tidychef/acquire/main.py
tidychef/acquire/ods/__init__.py
tidychef/acquire/ods/http_implemented.py
tidychef/acquire/ods/local_implemented.py
tidychef/acquire/python/__init__.py
tidychef/acquire/python/listoflists_implemented.py
tidychef/acquire/python/pipetable_implemented.py
tidychef/acquire/xls/__init__.py
tidychef/acquire/xls/http_implemented.py
tidychef/acquire/xls/local_implemented.py
tidychef/acquire/xls/shared.py
tidychef/acquire/xlsx/__init__.py
tidychef/acquire/xlsx/http_implemented.py
tidychef/acquire/xlsx/local_implemented.py
tidychef/acquire/xlsx/shared.py
tidychef/against/__init__.py
tidychef/against/implementations/__init__.py
tidychef/against/implementations/base.py
tidychef/against/implementations/items.py
tidychef/against/implementations/length.py
tidychef/against/implementations/numeric.py
tidychef/against/implementations/regex.py
tidychef/against/wrapper.py
tidychef/column/__init__.py
tidychef/column/base.py
tidychef/column/column.py
tidychef/datafuncs/README.md
tidychef/datafuncs/__init__.py
tidychef/datafuncs/common.py
tidychef/datafuncs/excel.py
tidychef/datafuncs/ordering.py
tidychef/direction/README.md
tidychef/direction/__init__.py
tidychef/direction/directions.py
tidychef/exceptions/__init__.py
tidychef/exceptions/badparams.py
tidychef/exceptions/cells.py
tidychef/exceptions/common.py
tidychef/exceptions/lookups.py
tidychef/lookup/__init__.py
tidychef/lookup/base.py
tidychef/lookup/engines/README.md
tidychef/lookup/engines/__init__.py
tidychef/lookup/engines/closest.py
tidychef/lookup/engines/constant.py
tidychef/lookup/engines/direct.py
tidychef/lookup/engines/horizontal_condition.py
tidychef/lookup/engines/within.py
tidychef/models/__init__.py
tidychef/models/source/__init__.py
tidychef/models/source/cell.py
tidychef-1.0.0.dist-info/LICENCE
tidychef-1.0.0.dist-info/METADATA
tidychef-1.0.0.dist-info/WHEEL
tidychef-1.0.0.dist-info/RECORD
