Metadata-Version: 2.3
Name: tidychef
Version: 1.0.0
Summary: Python framework for transforming tabulated data with visual relationships into tidy data
License: Apache 2.0
Author: mikeAdamss
Author-email: mikelovesbooks@gmail.com
Requires-Python: >=3.9,<4.0
Classifier: License :: Other/Proprietary License
Classifier: Programming Language :: Python :: 3
Classifier: Programming Language :: Python :: 3.9
Classifier: Programming Language :: Python :: 3.10
Classifier: Programming Language :: Python :: 3.11
Classifier: Programming Language :: Python :: 3.12
Classifier: Programming Language :: Python :: 3.13
Requires-Dist: cachecontrol (>=0.13.1,<0.14.0)
Requires-Dist: ezodf (>=0.3.2,<0.4.0)
Requires-Dist: filelock (>=3.12.2,<4.0.0)
Requires-Dist: jupyter (>=1.0.0,<2.0.0)
Requires-Dist: lxml (>=4.9.3,<5.0.0)
Requires-Dist: openpyxl (>=3.1.2,<4.0.0)
Requires-Dist: requests (>=2.31.0,<3.0.0)
Requires-Dist: tabulate (>=0.9.0,<0.10.0)
Requires-Dist: validators (>=0.20.0,<0.21.0)
Requires-Dist: xlrd (>=2.0.1,<3.0.0)
Project-URL: Repository, https://github.com/mikeAdamss/tidychef
